petcache/__init__.py
petcache/__main__.py
petcache/__version__.py
petcache/api.py
petcache/cache.py
petcache-0.0.1.dist-info/METADATA
petcache-0.0.1.dist-info/WHEEL
petcache-0.0.1.dist-info/licenses/LICENSE
petcache-0.0.1.dist-info/RECORD
