Metadata-Version: 2.4
Name: petcache
Version: 0.0.1
Summary: Simple persistent cache for texts for your pet projects
Project-URL: Homepage, https://github.com/alexeygrigorev/petcache
Project-URL: Repository, https://github.com/alexeygrigorev/petcache
Project-URL: Issues, https://github.com/alexeygrigorev/petcache/issues
Author-email: Alexey Grigorev <alexey@datatalks.club>
Maintainer-email: Alexey Grigorev <alexey@datatalks.club>
License: WTFPL
License-File: LICENSE
Keywords: cache
Classifier: Development Status :: 4 - Beta
Classifier: Intended Audience :: Developers
Classifier: License :: Other/Proprietary License
Classifier: Programming Language :: Python :: 3
Classifier: Programming Language :: Python :: 3.10
Classifier: Programming Language :: Python :: 3.11
Classifier: Programming Language :: Python :: 3.12
Classifier: Programming Language :: Python :: 3.13
Classifier: Topic :: Software Development :: Libraries :: Python Modules
Requires-Python: >=3.10
Requires-Dist: fastapi>=0.104.0
Requires-Dist: uvicorn[standard]>=0.24.0
